stdLogic.vhdl
LIBRARY ieee;
USE IEEE.std_logic_1164.ALL;

ENTITY stdLogic IS
END ENTITY;

ARCHITECTURE sim OF stdLogic IS
    SIGNAL sig1 : STD_LOGIC := '0';
    SIGNAL sig2 : STD_LOGIC;
    SIGNAL sig3 : STD_LOGIC;
BEGIN
    PROCESS IS
    BEGIN
    REPORT "Process f";
        WAIT FOR 10 ns;
        REPORT "Process A";
        sig1 <= NOT sig1;

    END PROCESS;

END ARCHITECTURE;

stdLogic.vcd
$date
  Sat Sep 10 18:49:28 2022
$end
$version
  GHDL v0
$end
$timescale
  1 fs
$end
$scope module standard $end
$upscope $end
$scope module std_logic_1164 $end
$upscope $end
$scope module stdlogic $end
$var reg 1 ! sig1 $end
$var reg 1 " sig2 $end
$var reg 1 # sig3 $end
$upscope $end
$enddefinitions $end
#0
0!
U"
U#
#10000000
1!
#20000000
0!
#30000000
1!
#40000000
0!
#50000000
1!
#60000000
0!
#70000000
1!
#80000000
0!
#90000000
1!
#100000000
0!
#110000000
1!
#120000000
0!
#130000000
1!
#140000000
0!
#150000000
1!
#160000000
0!
#170000000
1!
#180000000
0!
#190000000
1!
#200000000
0!
#210000000
1!
#220000000
0!
#230000000
1!
#240000000
0!
#250000000
1!
#260000000
0!
#270000000
1!
#280000000
0!
#290000000
1!
#300000000
0!
#310000000
1!
#320000000
0!
#330000000
1!
#340000000
0!
#350000000
1!
#360000000
0!
#370000000
1!
#380000000
0!
#390000000
1!
#400000000
0!
#410000000
1!
#420000000
0!
#430000000
1!
#440000000
0!
#450000000
1!
#460000000
0!
#470000000
1!
#480000000
0!
#490000000
1!
#500000000
0!
#510000000
1!
#520000000
0!
#530000000
1!
#540000000
0!
#550000000
1!
#560000000
0!
#570000000
1!
#580000000
0!
#590000000
1!
#600000000
0!
#610000000
1!
#620000000
0!
#630000000
1!
#640000000
0!
#650000000
1!
#660000000
0!
#670000000
1!
#680000000
0!
#690000000
1!
#700000000
0!
#710000000
1!
#720000000
0!
#730000000
1!
#740000000
0!
#750000000
1!
#760000000
0!
#770000000
1!
#780000000
0!
#790000000
1!
#800000000
0!
#810000000
1!
#820000000
0!
#830000000
1!
#840000000
0!
#850000000
1!
#860000000
0!
#870000000
1!
#880000000
0!
#890000000
1!
#900000000
0!
#910000000
1!
#920000000
0!
#930000000
1!
#940000000
0!
#950000000
1!
#960000000
0!
#970000000
1!
#980000000
0!
#990000000
1!
#1000000000
0!
#1010000000
1!
#1020000000
0!
#1030000000
1!
#1040000000
0!
#1050000000
1!
#1060000000
0!
#1070000000
1!
#1080000000
0!
#1090000000
1!
#1100000000
0!
#1110000000
1!
#1120000000
0!
#1130000000
1!
#1140000000
0!
#1150000000
1!
#1160000000
0!
#1170000000
1!
#1180000000
0!
#1190000000
1!
#1200000000
0!
#1210000000
1!
#1220000000
0!
#1230000000
1!
#1240000000
0!
#1250000000
1!
#1260000000
0!
#1270000000
1!
#1280000000
0!
#1290000000
1!
#1300000000
0!
#1310000000
1!
#1320000000
0!
#1330000000
1!
#1340000000
0!
#1350000000
1!
#1360000000
0!
#1370000000
1!
#1380000000
0!
#1390000000
1!
#1400000000
0!
#1410000000
1!
#1420000000
0!
#1430000000
1!
#1440000000
0!
#1450000000
1!
#1460000000
0!
#1470000000
1!
#1480000000
0!
#1490000000
1!
#1500000000
0!
#1510000000
1!
#1520000000
0!
#1530000000
1!
#1540000000
0!
#1550000000
1!
#1560000000
0!
#1570000000
1!
#1580000000
0!
#1590000000
1!
#1600000000
0!
#1610000000
1!
#1620000000
0!
#1630000000
1!
#1640000000
0!
#1650000000
1!
#1660000000
0!
#1670000000
1!
#1680000000
0!
#1690000000
1!
#1700000000
0!
#1710000000
1!
#1720000000
0!
#1730000000
1!
#1740000000
0!
#1750000000
1!
#1760000000
0!
#1770000000
1!
#1780000000
0!
#1790000000
1!
#1800000000
0!
#1810000000
1!
#1820000000
0!
#1830000000
1!
#1840000000
0!
#1850000000
1!
#1860000000
0!
#1870000000
1!
#1880000000
0!
#1890000000
1!
#1900000000
0!
#1910000000
1!
#1920000000
0!
#1930000000
1!
#1940000000
0!
#1950000000
1!
#1960000000
0!
#1970000000
1!
#1980000000
0!
#1990000000
1!
#2000000000
0!
#2010000000
1!
#2020000000
0!
#2030000000
1!
#2040000000
0!
#2050000000
1!
#2060000000
0!
#2070000000
1!
#2080000000
0!
#2090000000
1!
#2100000000
0!
#2110000000
1!
#2120000000
0!
#2130000000
1!
#2140000000
0!
#2150000000
1!
#2160000000
0!
#2170000000
1!
#2180000000
0!
#2190000000
1!
#2200000000
0!
#2210000000
1!
#2220000000
0!
#2230000000
1!
#2240000000
0!
#2250000000
1!
#2260000000
0!
#2270000000
1!
#2280000000
0!
#2290000000
1!
#2300000000
0!
#2310000000
1!
#2320000000
0!
#2330000000
1!
#2340000000
0!
#2350000000
1!
#2360000000
0!
#2370000000
1!
#2380000000
0!
#2390000000
1!
#2400000000
0!
#2410000000
1!
#2420000000
0!
#2430000000
1!
#2440000000
0!
#2450000000
1!
#2460000000
0!
#2470000000
1!
#2480000000
0!
#2490000000
1!
#2500000000
0!
#2510000000
1!
#2520000000
0!
#2530000000
1!
#2540000000
0!
#2550000000
1!
#2560000000
0!
#2570000000
1!
#2580000000
0!
#2590000000
1!
#2600000000
0!
#2610000000
1!
#2620000000
0!
#2630000000
1!
#2640000000
0!
#2650000000
1!
#2660000000
0!
#2670000000
1!
#2680000000
0!
#2690000000
1!
#2700000000
0!
#2710000000
1!
#2720000000
0!
#2730000000
1!
#2740000000
0!
#2750000000
1!
#2760000000
0!
#2770000000
1!
#2780000000
0!
#2790000000
1!
#2800000000
0!
#2810000000
1!
#2820000000
0!
#2830000000
1!
#2840000000
0!
#2850000000
1!
#2860000000
0!
#2870000000
1!
#2880000000
0!
#2890000000
1!
#2900000000
0!
#2910000000
1!
#2920000000
0!
#2930000000
1!
#2940000000
0!
#2950000000
1!
#2960000000
0!
#2970000000
1!
#2980000000
0!
#2990000000
1!
#3000000000
0!
#3010000000
1!
#3020000000
0!
#3030000000
1!
#3040000000
0!
#3050000000
1!
#3060000000
0!
#3070000000
1!
#3080000000
0!
#3090000000
1!
#3100000000
0!
#3110000000
1!
#3120000000
0!
#3130000000
1!
#3140000000
0!
#3150000000
1!
#3160000000
0!
#3170000000
1!
#3180000000
0!
#3190000000
1!
#3200000000
0!
#3210000000
1!
#3220000000
0!
#3230000000
1!
#3240000000
0!
#3250000000
1!
#3260000000
0!
#3270000000
1!
#3280000000
0!
#3290000000
1!
#3300000000
0!
#3310000000
1!
#3320000000
0!
#3330000000
1!
#3340000000
0!
#3350000000
1!
#3360000000
0!
#3370000000
1!
#3380000000
0!
#3390000000
1!
#3400000000
0!
#3410000000
1!
#3420000000
0!
#3430000000
1!
#3440000000
0!
#3450000000
1!
#3460000000
0!
#3470000000
1!
#3480000000
0!
#3490000000
1!
#3500000000
0!
#3510000000
1!
#3520000000
0!
#3530000000
1!
#3540000000
0!
#3550000000
1!
#3560000000
0!
#3570000000
1!
#3580000000
0!
#3590000000
1!
#3600000000
0!
#3610000000
1!
#3620000000
0!
#3630000000
1!
#3640000000
0!
#3650000000
1!
#3660000000
0!
#3670000000
1!
#3680000000
0!
#3690000000
1!
#3700000000
0!
#3710000000
1!
#3720000000
0!
#3730000000
1!
#3740000000
0!
#3750000000
1!
#3760000000
0!
#3770000000
1!
#3780000000
0!
#3790000000
1!
#3800000000
0!
#3810000000
1!
#3820000000
0!
#3830000000
1!
#3840000000
0!
#3850000000
1!
#3860000000
0!
#3870000000
1!
#3880000000
0!
#3890000000
1!
#3900000000
0!
#3910000000
1!
#3920000000
0!
#3930000000
1!
#3940000000
0!
#3950000000
1!
#3960000000
0!
#3970000000
1!
#3980000000
0!
#3990000000
1!
#4000000000
0!
#4010000000
1!
#4020000000
0!
#4030000000
1!
#4040000000
0!
#4050000000
1!
#4060000000
0!
#4070000000
1!
#4080000000
0!
#4090000000
1!
#4100000000
0!
#4110000000
1!
#4120000000
0!
#4130000000
1!
#4140000000
0!
#4150000000
1!
#4160000000
0!
#4170000000
1!
#4180000000
0!
#4190000000
1!
#4200000000
0!
#4210000000
1!
#4220000000
0!
#4230000000
1!
#4240000000
0!
#4250000000
1!
#4260000000
0!
#4270000000
1!
#4280000000
0!
#4290000000
1!
#4300000000
0!
#4310000000
1!
#4320000000
0!
#4330000000
1!
#4340000000
0!
#4350000000
1!
#4360000000
0!
#4370000000
1!
#4380000000
0!
#4390000000
1!
#4400000000
0!
#4410000000
1!
#4420000000
0!
#4430000000
1!
#4440000000
0!
#4450000000
1!
#4460000000
0!
#4470000000
1!
#4480000000
0!
#4490000000
1!
#4500000000
0!
#4510000000
1!
#4520000000
0!
#4530000000
1!
#4540000000
0!
#4550000000
1!
#4560000000
0!
#4570000000
1!
#4580000000
0!
#4590000000
1!
#4600000000
0!
#4610000000
1!
#4620000000
0!
#4630000000
1!
#4640000000
0!
#4650000000
1!
#4660000000
0!
#4670000000
1!
#4680000000
0!
#4690000000
1!
#4700000000
0!
#4710000000
1!
#4720000000
0!
#4730000000
1!
#4740000000
0!
#4750000000
1!
#4760000000
0!
#4770000000
1!
#4780000000
0!
#4790000000
1!
#4800000000
0!
#4810000000
1!
#4820000000
0!
#4830000000
1!
#4840000000
0!
#4850000000
1!
#4860000000
0!
#4870000000
1!
#4880000000
0!
#4890000000
1!
#4900000000
0!
#4910000000
1!
#4920000000
0!
#4930000000
1!
#4940000000
0!
#4950000000
1!
#4960000000
0!
#4970000000
1!
#4980000000
0!
#4990000000
1!
#5000000000
0!
#5010000000
1!
#5020000000
0!
#5030000000
1!
#5040000000
0!
#5050000000
1!
#5060000000
0!
#5070000000
1!
#5080000000
0!
#5090000000
1!
#5100000000
0!
#5110000000
1!
#5120000000
0!
#5130000000
1!
#5140000000
0!
#5150000000
1!
#5160000000
0!
#5170000000
1!
#5180000000
0!
#5190000000
1!
#5200000000
0!
#5210000000
1!
#5220000000
0!
#5230000000
1!
#5240000000
0!
#5250000000
1!
#5260000000
0!
#5270000000
1!
#5280000000
0!
#5290000000
1!
#5300000000
0!
#5310000000
1!
#5320000000
0!
#5330000000
1!
#5340000000
0!
#5350000000
1!
#5360000000
0!
#5370000000
1!
#5380000000
0!
#5390000000
1!
#5400000000
0!
#5410000000
1!
#5420000000
0!
#5430000000
1!
#5440000000
0!
#5450000000
1!
#5460000000
0!
#5470000000
1!
#5480000000
0!
#5490000000
1!
#5500000000
0!
#5510000000
1!
#5520000000
0!
#5530000000
1!
#5540000000
0!
#5550000000
1!
#5560000000
0!
#5570000000
1!
#5580000000
0!
#5590000000
1!
#5600000000
0!
#5610000000
1!
#5620000000
0!
#5630000000
1!
#5640000000
0!
#5650000000
1!
#5660000000
0!
#5670000000
1!
#5680000000
0!
#5690000000
1!
#5700000000
0!
#5710000000
1!
#5720000000
0!
#5730000000
1!
#5740000000
0!
#5750000000
1!
#5760000000
0!
#5770000000
1!
#5780000000
0!
#5790000000
1!
#5800000000
0!
#5810000000
1!
#5820000000
0!
#5830000000
1!
#5840000000
0!
#5850000000
1!
#5860000000
0!
#5870000000
1!
#5880000000
0!
#5890000000
1!
#5900000000
0!
#5910000000
1!
#5920000000
0!
#5930000000
1!
#5940000000
0!
#5950000000
1!
#5960000000
0!
#5970000000
1!
#5980000000
0!
#5990000000
1!
#6000000000
0!
#6010000000
1!
#6020000000
0!
#6030000000
1!
#6040000000
0!
#6050000000
1!
#6060000000
0!
#6070000000
1!
#6080000000
0!
#6090000000
1!
#6100000000
0!
#6110000000
1!
#6120000000
0!
#6130000000
1!
#6140000000
0!
#6150000000
1!
#6160000000
0!
#6170000000
1!
#6180000000
0!
#6190000000
1!
#6200000000
0!
#6210000000
1!
#6220000000
0!
#6230000000
1!
#6240000000
0!
#6250000000
1!
#6260000000
0!
#6270000000
1!
#6280000000
0!
#6290000000
1!
#6300000000
0!
#6310000000
1!
#6320000000
0!
#6330000000
1!
#6340000000
0!
#6350000000
1!
#6360000000
0!
#6370000000
1!
#6380000000
0!
#6390000000
1!
#6400000000
0!
#6410000000
1!
#6420000000
0!
#6430000000
1!
#6440000000
0!
#6450000000
1!
#6460000000
0!
#6470000000
1!
#6480000000
0!
#6490000000
1!
#6500000000
0!
#6510000000
1!
#6520000000
0!
#6530000000
1!
#6540000000
0!
#6550000000
1!
#6560000000
0!
#6570000000
1!
#6580000000
0!
#6590000000
1!
#6600000000
0!
#6610000000
1!
#6620000000
0!
#6630000000
1!
#6640000000
0!
#6650000000
1!
#6660000000
0!
#6670000000
1!
#6680000000
0!
#6690000000
1!
#6700000000
0!
#6710000000
1!
#6720000000
0!
#6730000000
1!
#6740000000
0!
#6750000000
1!
#6760000000
0!
#6770000000
1!
#6780000000
0!
#6790000000
1!
#6800000000
0!
#6810000000
1!
#6820000000
0!
#6830000000
1!
#6840000000
0!
#6850000000
1!
#6860000000
0!
#6870000000
1!
#6880000000
0!
#6890000000
1!
#6900000000
0!
#6910000000
1!
#6920000000
0!
#6930000000
1!
#6940000000
0!
#6950000000
1!
#6960000000
0!
#6970000000
1!
#6980000000
0!
#6990000000
1!
#7000000000
0!
#7010000000
1!
#7020000000
0!
#7030000000
1!
#7040000000
0!
#7050000000
1!
#7060000000
0!
#7070000000
1!
#7080000000
0!
#7090000000
1!
#7100000000
0!
#7110000000
1!
#7120000000
0!
#7130000000
1!
#7140000000
0!
#7150000000
1!
#7160000000
0!
#7170000000
1!
#7180000000
0!
#7190000000
1!
#7200000000
0!
#7210000000
1!
#7220000000
0!
#7230000000
1!
#7240000000
0!
#7250000000
1!
#7260000000
0!
#7270000000
1!
#7280000000
0!
#7290000000
1!
#7300000000
0!
#7310000000
1!
#7320000000
0!
#7330000000
1!
#7340000000
0!
#7350000000
1!
#7360000000
0!
#7370000000
1!
#7380000000
0!
#7390000000
1!
#7400000000
0!
#7410000000
1!
#7420000000
0!
#7430000000
1!
#7440000000
0!
#7450000000
1!
#7460000000
0!
#7470000000
1!
#7480000000
0!
#7490000000
1!
#7500000000
0!
#7510000000
1!
#7520000000
0!
#7530000000
1!
#7540000000
0!
#7550000000
1!
#7560000000
0!
#7570000000
1!
#7580000000
0!
#7590000000
1!
#7600000000
0!
#7610000000
1!
#7620000000
0!
#7630000000
1!
#7640000000
0!
#7650000000
1!
#7660000000
0!
#7670000000
1!
#7680000000
0!
#7690000000
1!
#7700000000
0!
#7710000000
1!
#7720000000
0!
#7730000000
1!
#7740000000
0!
#7750000000
1!
#7760000000
0!
#7770000000
1!
#7780000000
0!
#7790000000
1!
#7800000000
0!
#7810000000
1!
#7820000000
0!
#7830000000
1!
#7840000000
0!
#7850000000
1!
#7860000000
0!
#7870000000
1!
#7880000000
0!
#7890000000
1!
#7900000000
0!
#7910000000
1!
#7920000000
0!
#7930000000
1!
#7940000000
0!
#7950000000
1!
#7960000000
0!
#7970000000
1!
#7980000000
0!
#7990000000
1!
#8000000000
0!
#8010000000
1!
#8020000000
0!
#8030000000
1!
#8040000000
0!
#8050000000
1!
#8060000000
0!
#8070000000
1!
#8080000000
0!
#8090000000
1!
#8100000000
0!
#8110000000
1!
#8120000000
0!
#8130000000
1!
#8140000000
0!
#8150000000
1!
#8160000000
0!
#8170000000
1!
#8180000000
0!
#8190000000
1!
#8200000000
0!
#8210000000
1!
#8220000000
0!
#8230000000
1!
#8240000000
0!
#8250000000
1!
#8260000000
0!
#8270000000
1!
#8280000000
0!
#8290000000
1!
#8300000000
0!
#8310000000
1!
#8320000000
0!
#8330000000
1!
#8340000000
0!
#8350000000
1!
#8360000000
0!
#8370000000
1!
#8380000000
0!
#8390000000
1!
#8400000000
0!
#8410000000
1!
#8420000000
0!
#8430000000
1!
#8440000000
0!
#8450000000
1!
#8460000000
0!
#8470000000
1!
#8480000000
0!
#8490000000
1!
#8500000000
0!
#8510000000
1!
#8520000000
0!
#8530000000
1!
#8540000000
0!
#8550000000
1!
#8560000000
0!
#8570000000
1!
#8580000000
0!
#8590000000
1!
#8600000000
0!
#8610000000
1!
#8620000000
0!
#8630000000
1!
#8640000000
0!
#8650000000
1!
#8660000000
0!
#8670000000
1!
#8680000000
0!
#8690000000
1!
#8700000000
0!
#8710000000
1!
#8720000000
0!
#8730000000
1!
#8740000000
0!
#8750000000
1!
#8760000000
0!
#8770000000
1!
#8780000000
0!
#8790000000
1!
#8800000000
0!
#8810000000
1!
#8820000000
0!
#8830000000
1!
#8840000000
0!
#8850000000
1!
#8860000000
0!
#8870000000
1!
#8880000000
0!
#8890000000
1!
#8900000000
0!
#8910000000
1!
#8920000000
0!
#8930000000
1!
#8940000000
0!
#8950000000
1!
#8960000000
0!
#8970000000
1!
#8980000000
0!
#8990000000
1!
#9000000000
0!
#9010000000
1!
#9020000000
0!
#9030000000
1!
#9040000000
0!
#9050000000
1!
#9060000000
0!
#9070000000
1!
#9080000000
0!
#9090000000
1!
#9100000000
0!
#9110000000
1!
#9120000000
0!
#9130000000
1!
#9140000000
0!
#9150000000
1!
#9160000000
0!
#9170000000
1!
#9180000000
0!
#9190000000
1!
#9200000000
0!
#9210000000
1!
#9220000000
0!
#9230000000
1!
#9240000000
0!
#9250000000
1!
#9260000000
0!
#9270000000
1!
#9280000000
0!
#9290000000
1!
#9300000000
0!
#9310000000
1!
#9320000000
0!
#9330000000
1!
#9340000000
0!
#9350000000
1!
#9360000000
0!
#9370000000
1!
#9380000000
0!
#9390000000
1!
#9400000000
0!
#9410000000
1!
#9420000000
0!
#9430000000
1!
#9440000000
0!
#9450000000
1!
#9460000000
0!
#9470000000
1!
#9480000000
0!
#9490000000
1!
#9500000000
0!
#9510000000
1!
#9520000000
0!
#9530000000
1!
#9540000000
0!
#9550000000
1!
#9560000000
0!
#9570000000
1!
#9580000000
0!
#9590000000
1!
#9600000000
0!
#9610000000
1!
#9620000000
0!
#9630000000
1!
#9640000000
0!
#9650000000
1!
#9660000000
0!
#9670000000
1!
#9680000000
0!
#9690000000
1!
#9700000000
0!
#9710000000
1!
#9720000000
0!
#9730000000
1!
#9740000000
0!
#9750000000
1!
#9760000000
0!
#9770000000
1!
#9780000000
0!
#9790000000
1!
#9800000000
0!
#9810000000
1!
#9820000000
0!
#9830000000
1!
#9840000000
0!
#9850000000
1!
#9860000000
0!
#9870000000
1!
#9880000000
0!
#9890000000
1!
#9900000000
0!
#9910000000
1!
#9920000000
0!
#9930000000
1!
#9940000000
0!
#9950000000
1!
#9960000000
0!
#9970000000
1!
#9980000000
0!
#9990000000
1!
#10000000000
0!
#10010000000
1!
#10020000000
0!
#10030000000
1!
#10040000000
0!
#10050000000
1!
#10060000000
0!
#10070000000
1!
#10080000000
0!
#10090000000
1!
#10100000000
0!
#10110000000
1!
#10120000000
0!
#10130000000
1!
#10140000000
0!
#10150000000
1!
#10160000000
0!
#10170000000
1!
#10180000000
0!
#10190000000
1!
#10200000000
0!
#10210000000
1!
#10220000000
0!
#10230000000
1!
#10240000000
0!
#10250000000
1!
#10260000000
0!
#10270000000
1!
#10280000000
0!
#10290000000
1!
#10300000000
0!
#10310000000
1!
#10320000000
0!
#10330000000
1!
#10340000000
0!
#10350000000
1!
#10360000000
0!
#10370000000
1!
#10380000000
0!
#10390000000
1!
#10400000000
0!
#10410000000
1!
#10420000000
0!
#10430000000
1!
#10440000000
0!
#10450000000
1!
#10460000000
0!
#10470000000
1!
#10480000000
0!
#10490000000
1!
#10500000000
0!
#10510000000
1!
#10520000000
0!
#10530000000
1!
#10540000000
0!
#10550000000
1!
#10560000000
0!
#10570000000
1!
#10580000000
0!
#10590000000
1!
#10600000000
0!
#10610000000
1!
#10620000000
0!
#10630000000
1!
#10640000000
0!
#10650000000
1!
#10660000000
0!
#10670000000
1!
#10680000000
0!
#10690000000
1!
#10700000000
0!
#10710000000
1!
#10720000000
0!
#10730000000
1!
#10740000000
0!
#10750000000
1!
#10760000000
0!
#10770000000
1!
#10780000000
0!
#10790000000
1!
#10800000000
0!
#10810000000
1!
#10820000000
0!
#10830000000
1!
#10840000000
0!
#10850000000
1!
#10860000000
0!
#10870000000
1!
#10880000000
0!
#10890000000
1!
#10900000000
0!
#10910000000
1!
#10920000000
0!
#10930000000
1!
#10940000000
0!
#10950000000
1!
#10960000000
0!
#10970000000
1!
#10980000000
0!
#10990000000
1!
#11000000000
0!
#11010000000
1!
#11020000000
0!
#11030000000
1!
#11040000000
0!
#11050000000
1!
#11060000000
0!
#11070000000
1!
#11080000000
0!
#11090000000
1!
#11100000000
0!
#11110000000
1!
#11120000000
0!
#11130000000
1!
#11140000000
0!
#11150000000
1!
#11160000000
0!
#11170000000
1!
#11180000000
0!
#11190000000
1!
#11200000000
0!
#11210000000
1!
#11220000000
0!
#11230000000
1!
#11240000000
0!
#11250000000
1!
#11260000000
0!
#11270000000
1!
#11280000000
0!
#11290000000
1!
#11300000000
0!
#11310000000
1!
#11320000000
0!
#11330000000
1!
#11340000000
0!
#11350000000
1!
#11360000000
0!
#11370000000
1!
#11380000000
0!
#11390000000
1!
#11400000000
0!
#11410000000
1!
#11420000000
0!
#11430000000
1!
#11440000000
0!
#11450000000
1!
#11460000000
0!
#11470000000
1!
#11480000000
0!
#11490000000
1!
#11500000000
0!
#11510000000
1!
#11520000000
0!
#11530000000
1!
#11540000000
0!
#11550000000
1!
#11560000000
0!
#11570000000
1!
#11580000000
0!
#11590000000
1!
#11600000000
0!
#11610000000
1!
#11620000000
0!
#11630000000
1!
#11640000000
0!
#11650000000
1!
#11660000000
0!
#11670000000
1!
#11680000000
0!
#11690000000
1!
#11700000000
0!
#11710000000
1!
#11720000000
0!
#11730000000
1!
#11740000000
0!
#11750000000
1!
#11760000000
0!
#11770000000
1!
#11780000000
0!
#11790000000
1!
#11800000000
0!
#11810000000
1!
#11820000000
0!
#11830000000
1!
#11840000000
0!
#11850000000
1!
#11860000000
0!
#11870000000
1!
#11880000000
0!
#11890000000
1!
#11900000000
0!
#11910000000
1!
#11920000000
0!
#11930000000
1!
#11940000000
0!
#11950000000
1!
#11960000000
0!
#11970000000
1!
#11980000000
0!
#11990000000
1!
#12000000000
0!
#12010000000
1!
#12020000000
0!
#12030000000
1!
#12040000000
0!
#12050000000
1!
#12060000000
0!
#12070000000
1!
#12080000000
0!
#12090000000
1!
#12100000000
0!
#12110000000
1!
#12120000000
0!
#12130000000
1!
#12140000000
0!
#12150000000
1!
#12160000000
0!
#12170000000
1!
#12180000000
0!
#12190000000
1!
#12200000000
0!
#12210000000
1!
#12220000000
0!
#12230000000
1!
#12240000000
0!
#12250000000
1!
#12260000000
0!
#12270000000
1!
#12280000000
0!
#12290000000
1!
#12300000000
0!
#12310000000
1!
#12320000000
0!
#12330000000
1!
#12340000000
0!
#12350000000
1!
#12360000000
0!
#12370000000
1!
#12380000000
0!
#12390000000
1!
#12400000000
0!
#12410000000
1!
#12420000000
0!
#12430000000
1!
#12440000000
0!
#12450000000
1!
#12460000000
0!
#12470000000
1!
#12480000000
0!
#12490000000
1!
#12500000000
0!
#12510000000
1!
#12520000000
0!
#12530000000
1!
#12540000000
0!
#12550000000
1!
#12560000000
0!
#12570000000
1!
#12580000000
0!
#12590000000
1!
#12600000000
0!
#12610000000
1!
#12620000000
0!
#12630000000
1!
#12640000000
0!
#12650000000
1!
#12660000000
0!
#12670000000
1!
#12680000000
0!
#12690000000
1!
#12700000000
0!
#12710000000
1!
#12720000000
0!
#12730000000
1!
#12740000000
0!
#12750000000
1!
#12760000000
0!
#12770000000
1!
#12780000000
0!
#12790000000
1!
#12800000000
0!
#12810000000
1!
#12820000000
0!
#12830000000
1!
#12840000000
0!
#12850000000
1!
#12860000000
0!
#12870000000
1!
#12880000000
0!
#12890000000
1!
#12900000000
0!
#12910000000
1!
#12920000000
0!
#12930000000
1!
#12940000000
0!
#12950000000
1!
#12960000000
0!
#12970000000
1!
#12980000000
0!
#12990000000
1!
#13000000000
0!
#13010000000
1!
#13020000000
0!
#13030000000
1!
#13040000000
0!
#13050000000
1!
#13060000000
0!
#13070000000
1!
#13080000000
0!
#13090000000
1!
#13100000000
0!
#13110000000
1!
#13120000000
0!
#13130000000
1!
#13140000000
0!
#13150000000
1!
#13160000000
0!
#13170000000
1!
#13180000000
0!
#13190000000
1!
#13200000000
0!
#13210000000
1!
#13220000000
0!
#13230000000
1!
#13240000000
0!
#13250000000
1!
#13260000000
0!
#13270000000
1!
#13280000000
0!
#13290000000
1!
#13300000000
0!
#13310000000
1!
#13320000000
0!
#13330000000
1!
#13340000000
0!
#13350000000
1!
#13360000000
0!
#13370000000
1!
#13380000000
0!
#13390000000
1!
#13400000000
0!
#13410000000
1!
#13420000000
0!
#13430000000
1!
#13440000000
0!
#13450000000
1!
#13460000000
0!
#13470000000
1!
#13480000000
0!
#13490000000
1!
#13500000000
0!
#13510000000
1!
#13520000000
0!
#13530000000
1!
#13540000000
0!
#13550000000
1!
#13560000000
0!
#13570000000
1!
#13580000000
0!
#13590000000
1!
#13600000000
0!
#13610000000
1!
#13620000000
0!
#13630000000
1!
#13640000000
0!
#13650000000
1!
#13660000000
0!
#13670000000
1!
#13680000000
0!
#13690000000
1!
#13700000000
0!
#13710000000
1!
#13720000000
0!
#13730000000
1!
#13740000000
0!
#13750000000
1!
#13760000000
0!
#13770000000
1!
#13780000000
0!
#13790000000
1!
#13800000000
0!
#13810000000
1!
#13820000000
0!
#13830000000
1!
#13840000000
0!
#13850000000
1!
#13860000000
0!
#13870000000
1!
#13880000000
0!
#13890000000
1!
#13900000000
0!
#13910000000
1!
#13920000000
0!
#13930000000
1!
#13940000000
0!
#13950000000
1!
#13960000000
0!
#13970000000
1!
#13980000000
0!
#13990000000
1!
#14000000000
0!
#14010000000
1!
#14020000000
0!
#14030000000
1!
#14040000000
0!
#14050000000
1!
#14060000000
0!
#14070000000
1!
#14080000000
0!
#14090000000
1!
#14100000000
0!
#14110000000
1!
#14120000000
0!
#14130000000
1!
#14140000000
0!
#14150000000
1!
#14160000000
0!
#14170000000
1!
#14180000000
0!
#14190000000
1!
#14200000000
0!
#14210000000
1!
#14220000000
0!
#14230000000
1!
#14240000000
0!
#14250000000
1!
#14260000000
0!
#14270000000
1!
#14280000000
0!
#14290000000
1!
#14300000000
0!
#14310000000
1!
#14320000000
0!
#14330000000
1!
#14340000000
0!
#14350000000
1!
#14360000000
0!
#14370000000
1!
#14380000000
0!
#14390000000
1!
#14400000000
0!
#14410000000
1!
#14420000000
0!
#14430000000
1!
#14440000000
0!
#14450000000
1!
#14460000000
0!
#14470000000
1!
#14480000000
0!
#14490000000
1!
#14500000000
0!
#14510000000
1!
#14520000000
0!
#14530000000
1!
#14540000000
0!
#14550000000
1!
#14560000000
0!
#14570000000
1!
#14580000000
0!
#14590000000
1!
#14600000000
0!
#14610000000
1!
#14620000000
0!
#14630000000
1!
#14640000000
0!
#14650000000
1!
#14660000000
0!
#14670000000
1!
#14680000000
0!
#14690000000
1!
#14700000000
0!
#14710000000
1!
#14720000000
0!
#14730000000
1!
#14740000000
0!
#14750000000
1!
#14760000000
0!
#14770000000
1!
#14780000000
0!
#14790000000
1!
#14800000000
0!
#14810000000
1!
#14820000000
0!
#14830000000
1!
#14840000000
0!
#14850000000
1!
#14860000000
0!
#14870000000
1!
#14880000000
0!
#14890000000
1!
#14900000000
0!
#14910000000
1!
#14920000000
0!
#14930000000
1!
#14940000000
0!
#14950000000
1!
#14960000000
0!
#14970000000
1!
#14980000000
0!
#14990000000
1!
#15000000000
0!
#15010000000
1!
#15020000000
0!
#15030000000
1!
#15040000000
0!
#15050000000
1!
#15060000000
0!
#15070000000
1!
#15080000000
0!
#15090000000
1!
#15100000000
0!
#15110000000
1!
#15120000000
0!
#15130000000
1!
#15140000000
0!
#15150000000
1!
#15160000000
0!
#15170000000
1!
#15180000000
0!
#15190000000
1!
#15200000000
0!
#15210000000
1!
#15220000000
0!
#15230000000
1!
#15240000000
0!
#15250000000
1!
#15260000000
0!
#15270000000
1!
#15280000000
0!
#15290000000
1!
#15300000000
0!
#15310000000
1!
#15320000000
0!
#15330000000
1!
#15340000000
0!
#15350000000
1!
#15360000000
0!
#15370000000
1!
#15380000000
0!
#15390000000
1!
#15400000000
0!
#15410000000
1!
#15420000000
0!
#15430000000
1!
#15440000000
0!
#15450000000
1!
#15460000000
0!
#15470000000
1!
#15480000000
0!
#15490000000
1!
#15500000000
0!
#15510000000
1!
#15520000000
0!
#15530000000
1!
#15540000000
0!
#15550000000
1!
#15560000000
0!
#15570000000
1!
#15580000000
0!
#15590000000
1!
#15600000000
0!
#15610000000
1!
#15620000000
0!
#15630000000
1!
#15640000000
0!
#15650000000
1!
#15660000000
0!
#15670000000
1!
#15680000000
0!
#15690000000
1!
#15700000000
0!
#15710000000
1!
#15720000000
0!
#15730000000
1!
#15740000000
0!
#15750000000
1!
#15760000000
0!
#15770000000
1!
#15780000000
0!
#15790000000
1!
#15800000000
0!
#15810000000
1!
#15820000000
0!
#15830000000
1!
#15840000000
0!
#15850000000
1!
#15860000000
0!
#15870000000
1!
#15880000000
0!
#15890000000
1!
#15900000000
0!
#15910000000
1!
#15920000000
0!
#15930000000
1!
#15940000000
0!
#15950000000
1!
#15960000000
0!
#15970000000
1!
#15980000000
0!
#15990000000
1!
#16000000000
0!
#16010000000
1!
#16020000000
0!
#16030000000
1!
#16040000000
0!
#16050000000
1!
#16060000000
0!
#16070000000
1!
#16080000000
0!
#16090000000
1!
#16100000000
0!
#16110000000
1!
#16120000000
0!
#16130000000
1!
#16140000000
0!
#16150000000
1!
#16160000000
0!
#16170000000
1!
#16180000000
0!
#16190000000
1!
#16200000000
0!
#16210000000
1!
#16220000000
0!
#16230000000
1!
#16240000000
0!
#16250000000
1!
#16260000000
0!
#16270000000
1!
#16280000000
0!
#16290000000
1!
