exercice/compteur/compteur.vhdl
LIBRARY IEEE;
USE IEEE.std_logic_1164.ALL;
USE IEEE.numeric_std.ALL;

ENTITY compteur IS

    PORT (
        clk : IN STD_LOGIC;
        compt : OUT STD_LOGIC_VECTOR (0 TO 3)
    );

END compteur;

ARCHITECTURE compteur_4bit OF compteur IS
    SIGNAL cmpt_tmp : INTEGER RANGE 0 TO 15 := 0;
BEGIN
    compt <= STD_LOGIC_VECTOR(to_unsigned(cmpt_tmp, 4));
    ps_compt : PROCESS (clk)
    BEGIN
        IF rising_edge(clk) THEN
            cmpt_tmp <= cmpt_tmp + 1;
        END IF;
    END PROCESS ps_compt;
END compteur_4bit;

exercice/compteur/compteur_tb.vhdl
LIBRARY IEEE;
USE IEEE.std_logic_1164.ALL;
USE IEEE.numeric_std.ALL;
ENTITY compteur_tb IS

END compteur_tb;

ARCHITECTURE test OF compteur_tb IS
    --compenet
    COMPONENT compteur
        PORT (
            clk : IN STD_LOGIC;
            compt : OUT STD_LOGIC_VECTOR (0 TO 3)
        );

    END COMPONENT;
    --input 
    SIGNAL clk_tb : STD_LOGIC;
    -- SIGNAL cmpt_tm_tb : INTEGER RANGE 0 TO 15 := 0;

    --output
    SIGNAL compt_tb : STD_LOGIC_VECTOR(0 TO 3);

BEGIN
    -- compt_tb <= STD_LOGIC_VECTOR(to_unsigned(cmpt_tm_tb, 4));
    DUT : compteur PORT MAP(
        clk => clk_tb,
        compt => compt_tb

    );
    PROCESS

    BEGIN
        clk_tb <= '0';
        WAIT FOR 20 ns;
        clk_tb <= '1';
        WAIT FOR 20 ns;
        clk_tb <= '0';
        WAIT FOR 20 ns;
        clk_tb <= '1';
        WAIT FOR 20 ns;
        clk_tb <= '0';
        WAIT FOR 20 ns;
        clk_tb <= '1';
        WAIT FOR 20 ns;
        clk_tb <= '0';
        WAIT FOR 20 ns;
        clk_tb <= '1';
        WAIT FOR 20 ns;
        clk_tb <= '0';
        WAIT FOR 20 ns;
        clk_tb <= '1';
        WAIT FOR 20 ns;
        clk_tb <= '0';
        WAIT FOR 20 ns;
        clk_tb <= '1';
        WAIT FOR 20 ns;
    END PROCESS;

END test;

CONFIGURATION compt_confg OF compteur_tb IS
    FOR test
        FOR DUT : compteur USE ENTITY work.compteur(compteur)
            PORT MAP(clk => clk, compt => compt);
    END FOR; --DUT
END FOR; --bench_add
END CONFIGURATION compt_confg;

exercice/compteur/compteur_tb.vcd
$date
  Mon Sep 12 15:10:35 2022
$end
$version
  GHDL v0
$end
$timescale
  1 fs
$end
$scope module standard $end
$upscope $end
$scope module std_logic_1164 $end
$upscope $end
$scope module numeric_std $end
$upscope $end
$scope module compteur_tb $end
$var reg 1 ! clk_tb $end
$var reg 4 " compt_tb[0:3] $end
$scope module dut $end
$var reg 1 # clk $end
$var reg 4 $ compt[0:3] $end
$var integer 32 % cmpt_tmp $end
$upscope $end
$upscope $end
$enddefinitions $end
#0
0!
b0000 "
0#
b0000 $
b0 %
#20000000
1!
b0001 "
1#
b0001 $
b1 %
#40000000
0!
0#
#60000000
1!
b0010 "
1#
b0010 $
b10 %
#80000000
0!
0#
#100000000
1!
b0011 "
1#
b0011 $
b11 %
#120000000
0!
0#
#140000000
1!
b0100 "
1#
b0100 $
b100 %
#160000000
0!
0#
#180000000
1!
b0101 "
1#
b0101 $
b101 %
#200000000
0!
0#
#220000000
1!
b0110 "
1#
b0110 $
b110 %
#240000000
0!
0#
#260000000
1!
b0111 "
1#
b0111 $
b111 %
#280000000
0!
0#
#300000000
1!
b1000 "
1#
b1000 $
b1000 %
#320000000
0!
0#
#340000000
1!
b1001 "
1#
b1001 $
b1001 %
#360000000
0!
0#
#380000000
1!
b1010 "
1#
b1010 $
b1010 %
#400000000
0!
0#
#420000000
1!
b1011 "
1#
b1011 $
b1011 %
#440000000
0!
0#
#460000000
1!
b1100 "
1#
b1100 $
b1100 %
#480000000
0!
0#
#500000000
1!
b1101 "
1#
b1101 $
b1101 %
#520000000
0!
0#
#540000000
1!
b1110 "
1#
b1110 $
b1110 %
#560000000
0!
0#
#580000000
1!
b1111 "
1#
b1111 $
b1111 %
